django_feedme-2.0.1.dist-info/DESCRIPTION.rst
django_feedme-2.0.1.dist-info/METADATA
django_feedme-2.0.1.dist-info/RECORD
django_feedme-2.0.1.dist-info/WHEEL
django_feedme-2.0.1.dist-info/metadata.json
django_feedme-2.0.1.dist-info/top_level.txt
feedme/__init__.py
feedme/admin.py
feedme/apps.py
feedme/digest.py
feedme/forms.py
feedme/google_takeout.py
feedme/managers.py
feedme/mixins.py
feedme/models.py
feedme/tasks.py
feedme/tests.py
feedme/urls.py
feedme/utils.py
feedme/views.py
feedme/management/__init__.py
feedme/management/commands/__init__.py
feedme/management/commands/send_digest.py
feedme/management/commands/update_feeds.py
feedme/migrations/0001_initial.py
feedme/migrations/__init__.py
feedme/south_migrations/0001_initial.py
feedme/south_migrations/0002_auto__add_field_feeditem_read__add_field_feed_user.py
feedme/south_migrations/0003_auto__add_field_feeditem_feed.py
feedme/south_migrations/0004_auto__add_field_category_slug.py
feedme/south_migrations/0005_auto__add_field_feed_title.py
feedme/south_migrations/0006_auto__add_field_category_user.py
feedme/south_migrations/0007_auto__add_field_feed_last_update.py
feedme/south_migrations/0008_auto__chg_field_feed_url.py
feedme/south_migrations/0009_auto__add_field_feeditem_guid__add_field_feeditem_pub_date__add_field_.py
feedme/south_migrations/0010_auto__add_field_feeditem_date_fetched.py
feedme/south_migrations/__init__.py
feedme/static/feedme/js/scripts.js
feedme/static/feedme/js/waypoints/licenses.txt
feedme/static/feedme/js/waypoints/waypoints.js
feedme/static/feedme/js/waypoints/waypoints.min.js
feedme/templates/feedme/base.html
feedme/templates/feedme/feed_list.html
feedme/templates/feedme/takeout_form.html
feedme/templates/feedme/mail/digest.html
feedme/templates/feedme/mail/digest.txt
