Metadata-Version: 2.0
Name: django-feedme
Version: 2.0.1
Summary: Django Google Reader Replacement
Home-page: http://github.com/dstegelman/django-feedme
Author: Derek Stegelman
Author-email: email@stegelman.com
License: MIT
Platform: UNKNOWN
Classifier: Development Status :: 5 - Production/Stable
Classifier: Environment :: Web Environment
Classifier: Intended Audience :: Developers
Classifier: License :: OSI Approved :: MIT License
Classifier: Operating System :: OS Independent
Classifier: Programming Language :: Python
Classifier: Programming Language :: Python :: 2
Classifier: Programming Language :: Python :: 3
Classifier: Framework :: Django
Classifier: Framework :: Django :: 1.8
Classifier: Framework :: Django :: 1.9
Requires-Dist: django-bootstrap-static (>=2.0,<3.0)
Requires-Dist: django-infuse (>=0.3)
Requires-Dist: feedparser (==5.1.3,<6.0)
Requires-Dist: lxml
